s3dict/__init__.py
s3dict-0.1.0.dist-info/METADATA
s3dict-0.1.0.dist-info/WHEEL
s3dict-0.1.0.dist-info/RECORD
