Metadata-Version: 2.1
Name: s3dict
Version: 0.1.0
Summary: Distributed Python dictionary backed by S3
License: MIT
Author: Jackie Tung
Author-email: jackie.tung@gmail.com
Requires-Python: >=3.8
Classifier: License :: OSI Approved :: MIT License
Classifier: Programming Language :: Python :: 3
Classifier: Programming Language :: Python :: 3.8
Classifier: Programming Language :: Python :: 3.9
Classifier: Programming Language :: Python :: 3.10
Classifier: Programming Language :: Python :: 3.11
Classifier: Programming Language :: Python :: 3.12
Requires-Dist: boto3 (>=1.20)
